MANIFEST.in
README.rst
s3ftp.json
setup.py
cftp/__main__.py
cftp/base.py
cftp/base_exceptions.py
cftp/s3.py
cftp/s3_exceptions.py
cftp.egg-info/PKG-INFO
cftp.egg-info/SOURCES.txt
cftp.egg-info/dependency_links.txt
cftp.egg-info/entry_points.txt
cftp.egg-info/not-zip-safe
cftp.egg-info/requires.txt
cftp.egg-info/top_level.txt