Metadata-Version: 1.1
Name: cftp
Version: 0.4.1a0
Summary: FTP-like client for interacting with cloud storage
Home-page: http://github.com/duderevolucion/cftp
Author: Dude Revolucion
Author-email: duderevolucion@gmail.com
License: GNU
Keywords: cloud s3 amazon ftp
Platform: UNKNOWN
Classifier: Development Status :: 3 - Alpha
Classifier: License :: OSI Approved :: GNU General Public License v3 or later (GPLv3+)
Classifier: Programming Language :: Python :: 3.4
Classifier: Topic :: Utilities
